Workbook

Sheet Extracción
A1: Métrica | B1: Fecha operativa | C1: Importe | D1: Casilla | E1: Ejercicio | F1: Documento | G1: Notas
A2: Ingresos trabajo | B2: 44197 | C2: 49639.98 | D2: 0012 | E2: 2021 | F2: PDFDeclaracion_2021.pdf
A3: Retenciones trabajo | B3: 44197 | C3: 7734.2 | D3: 0596 | E3: 2021 | F3: PDFDeclaracion_2021.pdf
A4: Ingresos capital mobiliario | B4: 44197 | C4: 225.11 | D4: 0036 | E4: 2021 | F4: PDFDeclaracion_2021.pdf
A5: Ingresos inmobiliarios netos | B5: 44197 | C5: 31.49 | D5: 0155 | E5: 2021 | F5: PDFDeclaracion_2021.pdf
A6: Ganancias patrimoniales | B6: 44197 | C6: -1086.8 | D6: 0425 | E6: 2021 | F6: PDFDeclaracion_2021.pdf
A7: Base imponible general | B7: 44197 | C7: 44733.14 | D7: 0435 | E7: 2021 | F7: PDFDeclaracion_2021.pdf
A8: Base imponible ahorro | B8: 44197 | C8: 89.05 | D8: 0460 | E8: 2021 | F8: PDFDeclaracion_2021.pdf
A9: Cuota íntegra estatal | B9: 44197 | C9: 5607.59 | D9: 0545 | E9: 2021 | F9: PDFDeclaracion_2021.pdf
A10: Cuota íntegra autonómica | B10: 44197 | C10: 5352.11 | D10: 0546 | E10: 2021 | F10: PDFDeclaracion_2021.pdf
A11: Cuota líquida total | B11: 44197 | C11: 10959.7 | D11: 0587 | E11: 2021 | F11: PDFDeclaracion_2021.pdf
A12: Retenciones totales | B12: 44197 | C12: 7776.56 | D12: 0609 | E12: 2021 | F12: PDFDeclaracion_2021.pdf
A13: Resultado declaración | B13: 44197 | C13: 3183.14 | D13: 0670 | E13: 2021 | F13: PDFDeclaracion_2021.pdf
A14: Aportaciones pensiones | B14: 44197 | C14: 0 | E14: 2021 | F14: PDFDeclaracion_2021.pdf
A15: Ingresos totales | B15: 44197 | C15: =C2+C4+C5+C6 -> 48809.78 | D15: Fórmula | E15: 2021 | F15: PDFDeclaracion_2021.pdf | G15: Ingresos trabajo + capital mobiliario bruto + inmobiliarios netos + ganancias patrimoniales netas.
A16: Margen fiscal sobre ingresos | B16: 44197 | C16: =C15-C12-C13 -> 37850.08 | D16: Fórmula | E16: 2021 | F16: PDFDeclaracion_2021.pdf | G16: Ingresos totales - retenciones totales - resultado de la declaración.
A17: Ingresos trabajo | B17: 44562 | C17: 46396.85 | D17: 0012 | E17: 2022 | F17: PDFDeclaracion_2022.pdf
A18: Retenciones trabajo | B18: 44562 | C18: 8439.87 | D18: 0596 | E18: 2022 | F18: PDFDeclaracion_2022.pdf
A19: Ingresos capital mobiliario | B19: 44562 | C19: 0 | D19: 0036 | E19: 2022 | F19: PDFDeclaracion_2022.pdf
A20: Ingresos inmobiliarios netos | B20: 44562 | C20: 0 | E20: 2022 | F20: PDFDeclaracion_2022.pdf
A21: Ganancias patrimoniales | B21: 44562 | C21: -2125.49 | D21: 0425 | E21: 2022 | F21: PDFDeclaracion_2022.pdf
A22: Base imponible general | B22: 44562 | C22: 41447.76 | D22: 0435 | E22: 2022 | F22: PDFDeclaracion_2022.pdf
A23: Base imponible ahorro | B23: 44562 | C23: 0 | D23: 0460 | E23: 2022 | F23: PDFDeclaracion_2022.pdf
A24: Cuota íntegra estatal | B24: 44562 | C24: 4991.34 | D24: 0545 | E24: 2022 | F24: PDFDeclaracion_2022.pdf
A25: Cuota íntegra autonómica | B25: 44562 | C25: 4883.91 | D25: 0546 | E25: 2022 | F25: PDFDeclaracion_2022.pdf
A26: Cuota líquida total | B26: 44562 | C26: 9875.25 | D26: 0587 | E26: 2022 | F26: PDFDeclaracion_2022.pdf
A27: Retenciones totales | B27: 44562 | C27: 8439.87 | D27: 0609 | E27: 2022 | F27: PDFDeclaracion_2022.pdf
A28: Resultado declaración | B28: 44562 | C28: 1435.38 | D28: 0670 | E28: 2022 | F28: PDFDeclaracion_2022.pdf
A29: Aportaciones pensiones | B29: 44562 | C29: 0 | E29: 2022 | F29: PDFDeclaracion_2022.pdf
A30: Ingresos totales | B30: 44562 | C30: =C17+C19+C20+C21 -> 44271.36 | D30: Fórmula | E30: 2022 | F30: PDFDeclaracion_2022.pdf | G30: Ingresos trabajo + capital mobiliario bruto + inmobiliarios netos + ganancias patrimoniales netas.
A31: Margen fiscal sobre ingresos | B31: 44562 | C31: =C30-C27-C28 -> 34396.11 | D31: Fórmula | E31: 2022 | F31: PDFDeclaracion_2022.pdf | G31: Ingresos totales - retenciones totales - resultado de la declaración.
A32: Ingresos trabajo | B32: 44927 | C32: 53157.92 | D32: 0012 | E32: 2023 | F32: PDFDeclaracion - 2023.pdf
A33: Retenciones trabajo | B33: 44927 | C33: 11944.27 | D33: 0596 | E33: 2023 | F33: PDFDeclaracion - 2023.pdf
A34: Ingresos capital mobiliario | B34: 44927 | C34: 708.99 | D34: 0036 | E34: 2023 | F34: PDFDeclaracion - 2023.pdf
A35: Ingresos inmobiliarios netos | B35: 44927 | C35: 0 | E35: 2023 | F35: PDFDeclaracion - 2023.pdf
A36: Ganancias patrimoniales | B36: 44927 | C36: 2417.91 | D36: 0424 | E36: 2023 | F36: PDFDeclaracion - 2023.pdf
A37: Base imponible general | B37: 44927 | C37: 47727.53 | D37: 0435 | E37: 2023 | F37: PDFDeclaracion - 2023.pdf
A38: Base imponible ahorro | B38: 44927 | C38: 520.31 | D38: 0460 | E38: 2023 | F38: PDFDeclaracion - 2023.pdf
A39: Cuota íntegra estatal | B39: 44927 | C39: 6041.82 | D39: 0545 | E39: 2023 | F39: PDFDeclaracion - 2023.pdf
A40: Cuota íntegra autonómica | B40: 44927 | C40: 6001.75 | D40: 0546 | E40: 2023 | F40: PDFDeclaracion - 2023.pdf
A41: Cuota líquida total | B41: 44927 | C41: 11939.57 | D41: 0587 | E41: 2023 | F41: PDFDeclaracion - 2023.pdf
A42: Retenciones totales | B42: 44927 | C42: 12078.98 | D42: 0609 | E42: 2023 | F42: PDFDeclaracion - 2023.pdf
A43: Resultado declaración | B43: 44927 | C43: -139.41 | D43: 0670 | E43: 2023 | F43: PDFDeclaracion - 2023.pdf
A44: Aportaciones pensiones | B44: 44927 | C44: 868.68 | D44: 0492 | E44: 2023 | F44: PDFDeclaracion - 2023.pdf
A45: Ingresos totales | B45: 44927 | C45: =C32+C34+C35+C36 -> 56284.82 | D45: Fórmula | E45: 2023 | F45: PDFDeclaracion - 2023.pdf | G45: Ingresos trabajo + capital mobiliario bruto + inmobiliarios netos + ganancias patrimoniales netas.
A46: Margen fiscal sobre ingresos | B46: 44927 | C46: =C45-C42-C43 -> 44345.25 | D46: Fórmula | E46: 2023 | F46: PDFDeclaracion - 2023.pdf | G46: Ingresos totales - retenciones totales - resultado de la declaración.
A47: Ingresos trabajo | B47: 45292 | C47: 59896.2 | D47: 0012 | E47: 2024 | F47: PDFDeclaracion - 2024_mod.pdf
A48: Retenciones trabajo | B48: 45292 | C48: 14104.38 | D48: 0596 | E48: 2024 | F48: PDFDeclaracion - 2024_mod.pdf
A49: Ingresos capital mobiliario | B49: 45292 | C49: 1632.04 | D49: 0036 | E49: 2024 | F49: PDFDeclaracion - 2024_mod.pdf
A50: Ingresos inmobiliarios netos | B50: 45292 | C50: 0 | E50: 2024 | F50: PDFDeclaracion - 2024_mod.pdf
A51: Ganancias patrimoniales | B51: 45292 | C51: 12224.64 | D51: 0424 | E51: 2024 | F51: PDFDeclaracion - 2024_mod.pdf
A52: Base imponible general | B52: 45292 | C52: 54242.33 | D52: 0435 | E52: 2024 | F52: PDFDeclaracion - 2024_mod.pdf
A53: Base imponible ahorro | B53: 45292 | C53: 10100.64 | D53: 0460 | E53: 2024 | F53: PDFDeclaracion - 2024_mod.pdf
A54: Cuota íntegra estatal | B54: 45292 | C54: 8191.37 | D54: 0545 | E54: 2024 | F54: PDFDeclaracion - 2024_mod.pdf
A55: Cuota íntegra autonómica | B55: 45292 | C55: 8281.88 | D55: 0546 | E55: 2024 | F55: PDFDeclaracion - 2024_mod.pdf
A56: Cuota líquida total | B56: 45292 | C56: 16473.25 | D56: 0587 | E56: 2024 | F56: PDFDeclaracion - 2024_mod.pdf
A57: Retenciones totales | B57: 45292 | C57: 14413.61 | D57: 0609 | E57: 2024 | F57: PDFDeclaracion - 2024_mod.pdf
A58: Resultado declaración | B58: 45292 | C58: 2059.64 | D58: 0670 | E58: 2024 | F58: PDFDeclaracion - 2024_mod.pdf
A59: Aportaciones pensiones | B59: 45292 | C59: 905.6 | D59: 0492 | E59: 2024 | F59: PDFDeclaracion - 2024_mod.pdf
A60: Ingresos totales | B60: 45292 | C60: =C47+C49+C50+C51 -> 73752.88 | D60: Fórmula | E60: 2024 | F60: PDFDeclaracion - 2024_mod.pdf | G60: Ingresos trabajo + capital mobiliario bruto + inmobiliarios netos + ganancias patrimoniales netas.
A61: Margen fiscal sobre ingresos | B61: 45292 | C61: =C60-C57-C58 -> 57279.63 | D61: Fórmula | E61: 2024 | F61: PDFDeclaracion - 2024_mod.pdf | G61: Ingresos totales - retenciones totales - resultado de la declaración.
A62: Ingresos trabajo | B62: 45658 | C62: 67055.04 | D62: 0012 | E62: 2025 | F62: PDFDeclaracion - 2025.pdf
A63: Retenciones trabajo | B63: 45658 | C63: 16427.63 | D63: 0596 | E63: 2025 | F63: PDFDeclaracion - 2025.pdf
A64: Ingresos capital mobiliario | B64: 45658 | C64: 822.05 | D64: 0036 | E64: 2025 | F64: PDFDeclaracion - 2025.pdf
A65: Ingresos inmobiliarios netos | B65: 45658 | C65: 0 | E65: 2025 | F65: PDFDeclaracion - 2025.pdf
A66: Ganancias patrimoniales | B66: 45658 | C66: 1958.2 | D66: 0424 | E66: 2025 | F66: PDFDeclaracion - 2025.pdf
A67: Base imponible general | B67: 45658 | C67: 61204.32 | D67: 0435 | E67: 2025 | F67: PDFDeclaracion - 2025.pdf
A68: Base imponible ahorro | B68: 45658 | C68: 2704.76 | D68: 0460 | E68: 2025 | F68: PDFDeclaracion - 2025.pdf
A69: Cuota íntegra estatal | B69: 45658 | C69: 8655.69 | D69: 0545 | E69: 2025 | F69: PDFDeclaracion - 2025.pdf
A70: Cuota íntegra autonómica | B70: 45658 | C70: 9007.38 | D70: 0546 | E70: 2025 | F70: PDFDeclaracion - 2025.pdf
A71: Cuota líquida total | B71: 45658 | C71: 17663.07 | D71: 0587 | E71: 2025 | F71: PDFDeclaracion - 2025.pdf
A72: Retenciones totales | B72: 45658 | C72: 16486.39 | D72: 0609 | E72: 2025 | F72: PDFDeclaracion - 2025.pdf
A73: Resultado declaración | B73: 45658 | C73: 1106.02 | D73: 0670 | E73: 2025 | F73: PDFDeclaracion - 2025.pdf
A74: Aportaciones pensiones | B74: 45658 | C74: 1338.17 | D74: 0492 | E74: 2025 | F74: PDFDeclaracion - 2025.pdf
A75: Ingresos totales | B75: 45658 | C75: =C62+C64+C65+C66 -> 69835.29 | D75: Fórmula | E75: 2025 | F75: PDFDeclaracion - 2025.pdf | G75: Ingresos trabajo + capital mobiliario bruto + inmobiliarios netos + ganancias patrimoniales netas.
A76: Margen fiscal sobre ingresos | B76: 45658 | C76: =C75-C72-C73 -> 52242.88 | D76: Fórmula | E76: 2025 | F76: PDFDeclaracion - 2025.pdf | G76: Ingresos totales - retenciones totales - resultado de la declaración.

Sheet Resumen
A1: Métrica | B1: 2021 | C1: 2022 | D1: 2023 | E1: 2024 | F1: 2025
A2: Ingresos trabajo | B2: =Extracción!C2 -> 49639.98 | C2: =Extracción!C17 -> 46396.85 | D2: =Extracción!C32 -> 53157.92 | E2: =Extracción!C47 -> 59896.2 | F2: =Extracción!C62 -> 67055.04
A3: Retenciones trabajo | B3: =Extracción!C3 -> 7734.2 | C3: =Extracción!C18 -> 8439.87 | D3: =Extracción!C33 -> 11944.27 | E3: =Extracción!C48 -> 14104.38 | F3: =Extracción!C63 -> 16427.63
A4: Ingresos capital mobiliario | B4: =Extracción!C4 -> 225.11 | C4: =Extracción!C19 -> 0 | D4: =Extracción!C34 -> 708.99 | E4: =Extracción!C49 -> 1632.04 | F4: =Extracción!C64 -> 822.05
A5: Ingresos inmobiliarios netos | B5: =Extracción!C5 -> 31.49 | C5: =Extracción!C20 -> 0 | D5: =Extracción!C35 -> 0 | E5: =Extracción!C50 -> 0 | F5: =Extracción!C65 -> 0
A6: Ganancias patrimoniales | B6: =Extracción!C6 -> -1086.8 | C6: =Extracción!C21 -> -2125.49 | D6: =Extracción!C36 -> 2417.91 | E6: =Extracción!C51 -> 12224.64 | F6: =Extracción!C66 -> 1958.2
A7: Base imponible general | B7: =Extracción!C7 -> 44733.14 | C7: =Extracción!C22 -> 41447.76 | D7: =Extracción!C37 -> 47727.53 | E7: =Extracción!C52 -> 54242.33 | F7: =Extracción!C67 -> 61204.32
A8: Base imponible ahorro | B8: =Extracción!C8 -> 89.05 | C8: =Extracción!C23 -> 0 | D8: =Extracción!C38 -> 520.31 | E8: =Extracción!C53 -> 10100.64 | F8: =Extracción!C68 -> 2704.76
A9: Cuota íntegra estatal | B9: =Extracción!C9 -> 5607.59 | C9: =Extracción!C24 -> 4991.34 | D9: =Extracción!C39 -> 6041.82 | E9: =Extracción!C54 -> 8191.37 | F9: =Extracción!C69 -> 8655.69
A10: Cuota íntegra autonómica | B10: =Extracción!C10 -> 5352.11 | C10: =Extracción!C25 -> 4883.91 | D10: =Extracción!C40 -> 6001.75 | E10: =Extracción!C55 -> 8281.88 | F10: =Extracción!C70 -> 9007.38
A11: Cuota líquida total | B11: =Extracción!C11 -> 10959.7 | C11: =Extracción!C26 -> 9875.25 | D11: =Extracción!C41 -> 11939.57 | E11: =Extracción!C56 -> 16473.25 | F11: =Extracción!C71 -> 17663.07
A12: Retenciones totales | B12: =Extracción!C12 -> 7776.56 | C12: =Extracción!C27 -> 8439.87 | D12: =Extracción!C42 -> 12078.98 | E12: =Extracción!C57 -> 14413.61 | F12: =Extracción!C72 -> 16486.39
A13: Resultado declaración | B13: =Extracción!C13 -> 3183.14 | C13: =Extracción!C28 -> 1435.38 | D13: =Extracción!C43 -> -139.41 | E13: =Extracción!C58 -> 2059.64 | F13: =Extracción!C73 -> 1106.02
... A16: Margen fiscal sobre ingresos | B16: =Extracción!C16 -> 37850.08 | C16: =Extracción!C31 -> 34396.11 | D16: =Extracción!C46 -> 44345.25 | E16: =Extracción!C61 -> 57279.63 | F16: =Extracción!C76 -> 52242.88

Sheet Diccionario
A1: Métrica | B1: Definición / criterio de extracción
A2: Ingresos trabajo | B2: Total ingresos íntegros computables de rendimientos del trabajo. Casilla 0012.
A3: Retenciones trabajo | B3: Retenciones / pagos a cuenta por rendimientos del trabajo. Casilla 0596.
A4: Ingresos capital mobiliario | B4: Total de ingresos íntegros de capital mobiliario. Casilla 0036 cuando existe.
A5: Ingresos inmobiliarios netos | B5: Rentas inmobiliarias netas/imputadas. Se informa 0 si no aparece importe por tratarse de vivienda habitual.
A6: Ganancias patrimoniales | B6: Saldo neto de ganancias/pérdidas a integrar en base del ahorro: positivo casilla 0424 o negativo casilla 0425.
A7: Base imponible general | B7: Casilla 0435.
A8: Base imponible ahorro | B8: Casilla 0460.
A9: Cuota íntegra estatal | B9: Casilla 0545.
A10: Cuota íntegra autonómica | B10: Casilla 0546.
A11: Cuota líquida total | B11: Cuota líquida incrementada total / suma cuota líquida estatal y autonómica. Casilla 0587.
A12: Retenciones totales | B12: Total pagos a cuenta. Casilla 0609.
... A16: Margen fiscal sobre ingresos | B16: Fórmula MoneyMap: ingresos totales - retenciones totales - resultado de la declaración.
